pychroma/Autocomplete.py
pychroma/Connection.py
pychroma/Controller.py
pychroma/Device.py
pychroma/Sketch.py
pychroma/__init__.py
pychroma/map.json
pychroma-0.0.2.dist-info/LICENSE
pychroma-0.0.2.dist-info/METADATA
pychroma-0.0.2.dist-info/WHEEL
pychroma-0.0.2.dist-info/top_level.txt
pychroma-0.0.2.dist-info/RECORD
