Metadata-Version: 2.1
Name: pychroma
Version: 0.0.2
Summary: Python library for accessing the Razer Chroma SDK
Home-page: https://github.com/morswin22/pychroma
Author: Patryk Janiak
Author-email: xmorswinx@gmail.com
License: MIT
Platform: UNKNOWN
Classifier: Programming Language :: Python :: 3
Classifier: License :: OSI Approved :: MIT License
Classifier: Operating System :: OS Independent
Requires-Python: >=3.6
Requires-Dist: requests (>=2.23.0)
Requires-Dist: pynput (>=1.6.8)
